mpp/__init__.py
mpp/main.py
mpp/resources/default.ico
mpp/resources/main.py.pattern
mpp/resources/nsis.pattern
mpp/resources/questions.json
mpp/resources/spec.pattern
mpp/src/__init__.py
mpp/src/commands/__init__.py
mpp/src/commands/config.py
mpp/src/commands/freeze.py
mpp/src/commands/installer.py
mpp/src/commands/setup.py
mpp/src/commands/version.py
mpp/src/utils/__init__.py
mpp/src/utils/ask.py
mpp/src/utils/config_file.py
mpp/src/utils/constants.py
mpp/src/utils/download.py
mpp/src/utils/files.py
mpp-0.1.9.dist-info/LICENSE
mpp-0.1.9.dist-info/METADATA
mpp-0.1.9.dist-info/WHEEL
mpp-0.1.9.dist-info/entry_points.txt
mpp-0.1.9.dist-info/top_level.txt
mpp-0.1.9.dist-info/RECORD
