Metadata-Version: 2.1
Name: mpp
Version: 0.1.9
Summary: My Python Project: a command-line tool to create a Python project
Home-page: https://github.com/deplanty/mpp
Author: deplanty
License: UNKNOWN
Platform: UNKNOWN
Classifier: Natural Language :: English
Classifier: Operating System :: Microsoft :: Windows
Classifier: Environment :: Console
Classifier: Programming Language :: Python :: 3
Classifier: License :: OSI Approved :: GNU General Public License v3 (GPLv3)
Requires-Python: >=3.7
